{
  "manifest": {
    "author": "KAISER",
    "version": "0.0.1",
    "name": "IX THE NIHILITY",
    "updater": "https://raw.githubusercontent.com/kaiser1433435/IX-THE-NIHILITY/refs/heads/main/IX_THE_NIHILITY.json",
    "transparency_mode": 3
  },
  "background": {
    "url": "https://raw.githubusercontent.com/kaiser1433435/nihility-wallpaperrr/refs/heads/main/TRUE%20NIHILITY.png",
    "overlay_alpha": 160
  },
  "simple_colors": {
    "accent": -2255617,
    "mention_highlight": 2076667636,
    "background": 0,
    "background_secondary": 0,
    "input_background": 5198940,
    "active_channel": -1612334342,
    "statusbar": 2105893,
    "blocked_bg": 0
  },
  "colors": {
    "uikit_btn_bg_color_selector_red": -4038938,
    "link": -2515975
  },
  "drawable_tints": {
    "ic_status_online_16dp": -2383623,
    "ic_status_dnd_16dp": -7261521,
    "ic_status_idle_16dp": -4227105
  }
}
